probeCOCOATek/__init__.py
probeCOCOATek/__main__.py
probeCOCOATek/cli.py
probeCOCOATek/probeCOCOATek.py
probeCOCOATek/TemporaryExposureKey/TemporaryExposureKey_pb2.py
probeCOCOATek/TemporaryExposureKey/__init__.py
probeCOCOATek-9.20210911.dist-info/LICENSE
probeCOCOATek-9.20210911.dist-info/METADATA
probeCOCOATek-9.20210911.dist-info/WHEEL
probeCOCOATek-9.20210911.dist-info/entry_points.txt
probeCOCOATek-9.20210911.dist-info/top_level.txt
probeCOCOATek-9.20210911.dist-info/RECORD
