Metadata-Version: 2.1
Name: probeCOCOATek
Version: 9.20210911
Summary: Probe TemporaryExposureKeys and Files of Exposure Notifications System in Japan a.k.a. COCOA.
Home-page: https://github.com/rocaz/probeCOCOATek
Author: ROCA
Author-email: rocaznet@gmail.com
License: MIT
Keywords: python python3 exposure-notification temporary-exposure-key cocoa cli cocoa-debugging
Platform: UNKNOWN
Classifier: Development Status :: 5 - Production/Stable
Classifier: Environment :: Console
Classifier: Intended Audience :: Developers
Classifier: Intended Audience :: System Administrators
Classifier: License :: OSI Approved :: MIT License
Classifier: Natural Language :: English
Classifier: Programming Language :: Python
Classifier: Programming Language :: Python :: 3 :: Only
Classifier: Programming Language :: Python :: 3.6
Classifier: Programming Language :: Python :: 3.7
Classifier: Programming Language :: Python :: 3.8
Classifier: Programming Language :: Python :: 3.9
Classifier: Topic :: Utilities
Requires-Python: >=3.6
Requires-Dist: pytz
Requires-Dist: protobuf
Requires-Dist: python-dateutil
Requires-Dist: requests
Requires-Dist: urllib3
